SafeVaultDB/__init__.py
SafeVaultDB/cli.py
SafeVaultDB/database.py
SafeVaultDB-1.0.2.dist-info/METADATA
SafeVaultDB-1.0.2.dist-info/WHEEL
SafeVaultDB-1.0.2.dist-info/entry_points.txt
SafeVaultDB-1.0.2.dist-info/top_level.txt
SafeVaultDB-1.0.2.dist-info/RECORD
