Metadata-Version: 2.1
Name: SafeVaultDB
Version: 1.0.2
Summary: a free database library for python
Home-page: https://github.com/RGB-CAT/SafeVaultDB-Python
Author: RGB_CATT
Author-email: <RGBCAT@duck.com>
Keywords: python,database
Classifier: Programming Language :: Python :: 3
Classifier: Operating System :: MacOS :: MacOS X
Classifier: Operating System :: Microsoft :: Windows
Requires-Dist: cryptography
